{
  "node_modules/.pnpm/@sveltejs+kit@1.0.0-next.511_svelte@3.50.1+vite@3.1.6/node_modules/@sveltejs/kit/src/runtime/client/start.js": {
    "file": "_app/immutable/start-d917aea7.js",
    "src": "node_modules/.pnpm/@sveltejs+kit@1.0.0-next.511_svelte@3.50.1+vite@3.1.6/node_modules/@sveltejs/kit/src/runtime/client/start.js",
    "isEntry": true,
    "imports": [
      "_index-10a89592.js",
      "_singletons-415ee607.js"
    ],
    "dynamicImports": [
      ".svelte-kit/generated/nodes/0.js",
      ".svelte-kit/generated/nodes/1.js",
      ".svelte-kit/generated/nodes/2.js"
    ]
  },
  "node_modules/.pnpm/@sveltejs+kit@1.0.0-next.511_svelte@3.50.1+vite@3.1.6/node_modules/@sveltejs/kit/src/runtime/components/layout.svelte": {
    "file": "_app/immutable/components/layout.svelte-d21b60a8.js",
    "src": "node_modules/.pnpm/@sveltejs+kit@1.0.0-next.511_svelte@3.50.1+vite@3.1.6/node_modules/@sveltejs/kit/src/runtime/components/layout.svelte",
    "isEntry": true,
    "imports": [
      "_index-10a89592.js"
    ]
  },
  "node_modules/.pnpm/@sveltejs+kit@1.0.0-next.511_svelte@3.50.1+vite@3.1.6/node_modules/@sveltejs/kit/src/runtime/components/error.svelte": {
    "file": "_app/immutable/components/error.svelte-77e19689.js",
    "src": "node_modules/.pnpm/@sveltejs+kit@1.0.0-next.511_svelte@3.50.1+vite@3.1.6/node_modules/@sveltejs/kit/src/runtime/components/error.svelte",
    "isEntry": true,
    "imports": [
      "_index-10a89592.js",
      "_singletons-415ee607.js"
    ]
  },
  "src/routes/+page.svelte": {
    "file": "_app/immutable/components/pages/_page.svelte-ba168e25.js",
    "src": "src/routes/+page.svelte",
    "isEntry": true,
    "imports": [
      "_index-10a89592.js"
    ],
    "css": [
      "_app/immutable/assets/_page-b9a5fc18.css"
    ]
  },
  "src/routes/+layout.ts": {
    "file": "_app/immutable/modules/pages/_layout.ts-20159c1e.js",
    "src": "src/routes/+layout.ts",
    "isEntry": true,
    "imports": [
      "__layout-c6f71c43.js"
    ]
  },
  "_singletons-415ee607.js": {
    "file": "_app/immutable/chunks/singletons-415ee607.js",
    "imports": [
      "_index-10a89592.js"
    ]
  },
  "_index-10a89592.js": {
    "file": "_app/immutable/chunks/index-10a89592.js"
  },
  "__layout-c6f71c43.js": {
    "file": "_app/immutable/chunks/_layout-c6f71c43.js",
    "css": [
      "_app/immutable/assets/_layout-4689cc21.css"
    ]
  },
  ".svelte-kit/generated/nodes/0.js": {
    "file": "_app/immutable/chunks/0-9b1ea551.js",
    "src": ".svelte-kit/generated/nodes/0.js",
    "isDynamicEntry": true,
    "imports": [
      "__layout-c6f71c43.js",
      "node_modules/.pnpm/@sveltejs+kit@1.0.0-next.511_svelte@3.50.1+vite@3.1.6/node_modules/@sveltejs/kit/src/runtime/components/layout.svelte"
    ]
  },
  ".svelte-kit/generated/nodes/1.js": {
    "file": "_app/immutable/chunks/1-455005f4.js",
    "src": ".svelte-kit/generated/nodes/1.js",
    "isDynamicEntry": true,
    "imports": [
      "node_modules/.pnpm/@sveltejs+kit@1.0.0-next.511_svelte@3.50.1+vite@3.1.6/node_modules/@sveltejs/kit/src/runtime/components/error.svelte"
    ]
  },
  ".svelte-kit/generated/nodes/2.js": {
    "file": "_app/immutable/chunks/2-41310879.js",
    "src": ".svelte-kit/generated/nodes/2.js",
    "isDynamicEntry": true,
    "imports": [
      "src/routes/+page.svelte"
    ]
  },
  "src/routes/+page.css": {
    "file": "_app/immutable/assets/_page-b9a5fc18.css",
    "src": "src/routes/+page.css"
  },
  "_layout.css": {
    "file": "_app/immutable/assets/_layout-4689cc21.css",
    "src": "_layout.css"
  }
}